{
    "billing_address_1": "135 Eastern Parkway",
    "billing_address_2": "",
    "billing_apt_suite": "APT 15G",
    "billing_city": "Brooklyn",
    "billing_country": "United States",
    "billing_country_abbrv": "USA",
    "billing_state": "New York",
    "billing_state_abbrv": "NY",
    "billing_zip": "11238",
    "card_cvv": "123",
    "card_exp_month": "06",
    "card_exp_year": "20",
    "card_number": "4060688027480152",
    "card_type": "Visa",
    "email": "ayinope@gmail.com",
    "first_name": "Kelvin",
    "last_name": "Fichter",
    "name_on_card": "Kelvin Fichter",
    "phone_number": "3473661509",
    "shipping_address_1": "135 Eastern Parkway",
    "shipping_address_2": "",
    "shipping_apt_suite": "APT 15G",
    "shipping_city": "Brooklyn",
    "shipping_country": "United States",
    "shipping_country_abbrv": "USA",
    "shipping_state": "New York",
    "shipping_state_abbrv": "NY",
    "shipping_zip": "11238"
}